dialectical_framework/__init__.py
dialectical_framework/ai_dto/__init__.py
dialectical_framework/ai_dto/action_plan_dto.py
dialectical_framework/ai_dto/causal_cycle_assessment_dto.py
dialectical_framework/ai_dto/causal_cycle_dto.py
dialectical_framework/ai_dto/causal_cycles_deck_dto.py
dialectical_framework/ai_dto/constructive_convergence_transition_audit_dto.py
dialectical_framework/ai_dto/dialectical_component_dto.py
dialectical_framework/ai_dto/dialectical_components_deck_dto.py
dialectical_framework/ai_dto/dto_mapper.py
dialectical_framework/ai_dto/reciprocal_solution_dto.py
dialectical_framework/ai_dto/transition_summary_dto.py
dialectical_framework/analyst/__init__.py
dialectical_framework/analyst/consultant.py
dialectical_framework/analyst/decorator_action_reflection.py
dialectical_framework/analyst/decorator_discrete_spiral.py
dialectical_framework/analyst/decorator_discrete_spiral_audited.py
dialectical_framework/analyst/domain/__init__.py
dialectical_framework/analyst/domain/assessable_cycle.py
dialectical_framework/analyst/domain/cycle.py
dialectical_framework/analyst/domain/interpretation.py
dialectical_framework/analyst/domain/rationale.py
dialectical_framework/analyst/domain/spiral.py
dialectical_framework/analyst/domain/transformation.py
dialectical_framework/analyst/domain/transition.py
dialectical_framework/analyst/domain/transition_cell_to_cell.py
dialectical_framework/analyst/domain/transition_segment_to_segment.py
dialectical_framework/analyst/strategic_consultant.py
dialectical_framework/analyst/think_action_reflection.py
dialectical_framework/analyst/think_constructive_convergence.py
dialectical_framework/analyst/think_constructive_convergence_auditor.py
dialectical_framework/analyst/wheel_builder_transition_calculator.py
dialectical_framework/brain.py
dialectical_framework/dialectical_reasoning.py
dialectical_framework/enums/__init__.py
dialectical_framework/enums/causality_type.py
dialectical_framework/enums/di.py
dialectical_framework-0.7.6.dist-info/LICENSE
dialectical_framework-0.7.6.dist-info/METADATA
dialectical_framework-0.7.6.dist-info/WHEEL
dialectical_framework-0.7.6.dist-info/RECORD
