Metadata-Version: 2.3
Name: dialectical-framework
Version: 0.7.6
Summary: A dialectical framework for augmented intelligence. AI reasoning powered with dialectics supports humans in: system optimization (psychology, engineering, business, politics, etc.); dispute resolution (mediation, conflicts, negotiations, etc.); decision-making (dilemmas, challenging situations, win-win, etc.).
License: MIT
Keywords: dialectics,dialectical-reasoning,synthesis,thesis-antithesis,ai,artificial-intelligence,llm,reasoning-framework,philosophy,logic,argumentation,conflict-resolution,decision-making,critical-thinking,semantic-graph,mirascope,pydantic,wisdom-units,polarity-reasoning
Author: Evaldas Taroza
Author-email: evaldas@dialexity.com
Requires-Python: >=3.11,<4.0
Classifier: Development Status :: 4 - Beta
Classifier: Environment :: Console
Classifier: Framework :: Pydantic
Classifier: Intended Audience :: Developers
Classifier: Intended Audience :: Education
Classifier: Intended Audience :: Science/Research
Classifier: License :: OSI Approved :: MIT License
Classifier: Natural Language :: English
Classifier: Operating System :: OS Independent
Classifier: Programming Language :: Python :: 3
Classifier: Programming Language :: Python :: 3.11
Classifier: Programming Language :: Python :: 3.12
Classifier: Programming Language :: Python :: 3.13
Classifier: Topic :: Education
Classifier: Topic :: Office/Business :: Financial :: Investment
Classifier: Topic :: Scientific/Engineering :: Artificial Intelligence
Classifier: Topic :: Scientific/Engineering :: Human Machine Interfaces
Classifier: Topic :: Sociology
Classifier: Topic :: Software Development :: Libraries :: Python Modules
Classifier: Topic :: Text Processing :: Linguistic
Requires-Dist: dependency-injector (>=4.48.2,<5.0.0)
Requires-Dist: litellm (>=1.79.3,<2.0.0)
Requires-Dist: mirascope[anthropic,azure,bedrock,langfuse,openai,tenacity] (>=1.25.7,<2.0.0)
Requires-Dist: python-dotenv (>=1.2.1,<2.0.0)
Requires-Dist: tabulate (>=0.9.0,<0.10.0)
Project-URL: Homepage, https://github.com/dialexity/dialectical-framework
Project-URL: Repository, https://github.com/dialexity/dialectical-framework
